corbado_python_sdk/__init__.py
corbado_python_sdk/config.py
corbado_python_sdk/corbado_sdk.py
corbado_python_sdk/py.typed
corbado_python_sdk/entities/__init__.py
corbado_python_sdk/entities/user_entity.py
corbado_python_sdk/exceptions/__init__.py
corbado_python_sdk/exceptions/server_exception.py
corbado_python_sdk/exceptions/standard_exception.py
corbado_python_sdk/exceptions/token_validation_exception.py
corbado_python_sdk/generated/__init__.py
corbado_python_sdk/generated/api_client.py
corbado_python_sdk/generated/api_response.py
corbado_python_sdk/generated/configuration.py
corbado_python_sdk/generated/exceptions.py
corbado_python_sdk/generated/py.typed
corbado_python_sdk/generated/rest.py
corbado_python_sdk/generated/api/__init__.py
corbado_python_sdk/generated/api/auth_events_api.py
corbado_python_sdk/generated/api/challenges_api.py
corbado_python_sdk/generated/api/client_envs_api.py
corbado_python_sdk/generated/api/connect_tokens_api.py
corbado_python_sdk/generated/api/identifiers_api.py
corbado_python_sdk/generated/api/passkey_challenges_api.py
corbado_python_sdk/generated/api/passkey_events_api.py
corbado_python_sdk/generated/api/passkeys_api.py
corbado_python_sdk/generated/api/password_managers_api.py
corbado_python_sdk/generated/api/project_config_api.py
corbado_python_sdk/generated/api/sessions_api.py
corbado_python_sdk/generated/api/users_api.py
corbado_python_sdk/generated/api/webhook_endpoints_api.py
corbado_python_sdk/generated/models/__init__.py
corbado_python_sdk/generated/models/aaguid_details.py
corbado_python_sdk/generated/models/append_history_data.py
corbado_python_sdk/generated/models/auth_event.py
corbado_python_sdk/generated/models/auth_event_create_req.py
corbado_python_sdk/generated/models/auth_event_method.py
corbado_python_sdk/generated/models/auth_event_status.py
corbado_python_sdk/generated/models/auth_event_type.py
corbado_python_sdk/generated/models/challenge.py
corbado_python_sdk/generated/models/challenge_create_req.py
passkeys-2.0.3.dist-info/licenses/LICENSE
passkeys-2.0.3.dist-info/METADATA
passkeys-2.0.3.dist-info/WHEEL
passkeys-2.0.3.dist-info/top_level.txt
passkeys-2.0.3.dist-info/RECORD
