Metadata-Version: 2.4
Name: passkeys
Version: 2.0.3
Summary: Corbado SDK
Home-page: https://github.com/corbado/corbado-python
Author: Corbado team
Author-email: support@corbado.com
Keywords: Corbado,Corbado Python SDK
Classifier: Development Status :: 5 - Production/Stable
Classifier: Intended Audience :: Developers
Classifier: License :: OSI Approved :: MIT License
Classifier: Programming Language :: Python
Classifier: Programming Language :: Python :: 3.8
Classifier: Programming Language :: Python :: 3.9
Classifier: Programming Language :: Python :: 3.10
Classifier: Programming Language :: Python :: 3.11
Classifier: Programming Language :: Python :: 3.12
Classifier: Operating System :: OS Independent
Classifier: Topic :: Software Development :: Libraries :: Python Modules
License-File: LICENSE
Requires-Dist: urllib3>=1.25.3
Requires-Dist: python-dateutil
Requires-Dist: pydantic>=2
Requires-Dist: typing-extensions>=4.7.1
Requires-Dist: pyopenssl
Requires-Dist: PyJWT
Provides-Extra: test
Requires-Dist: pytest~=7.1.3; extra == "test"
Requires-Dist: pytest-cov>=2.8.1; extra == "test"
Requires-Dist: pytest-randomly>=3.12.0; extra == "test"
Provides-Extra: flake8
Requires-Dist: flake8>=7.0.0; extra == "flake8"
Requires-Dist: pep8-naming; extra == "flake8"
Requires-Dist: flake8-builtins; extra == "flake8"
Requires-Dist: flake8-bugbear; extra == "flake8"
Requires-Dist: flake8-isort; extra == "flake8"
Requires-Dist: darglint; extra == "flake8"
Requires-Dist: flake8-bandit; extra == "flake8"
Requires-Dist: flake8-return; extra == "flake8"
Requires-Dist: flake8-docstrings>=1.7.0; extra == "flake8"
Provides-Extra: mypy
Requires-Dist: mypy; extra == "mypy"
Provides-Extra: tox-gh
Requires-Dist: tox-gh-actions; extra == "tox-gh"
Provides-Extra: tox
Requires-Dist: tox>=4.0.0; extra == "tox"
Dynamic: author
Dynamic: author-email
Dynamic: classifier
Dynamic: description
Dynamic: description-content-type
Dynamic: home-page
Dynamic: keywords
Dynamic: license-file
Dynamic: requires-dist
Dynamic: summary
